odoo/addons/stock_picking_product_barcode_report/README.rst
odoo/addons/stock_picking_product_barcode_report/__init__.py
odoo/addons/stock_picking_product_barcode_report/__manifest__.py
odoo/addons/stock_picking_product_barcode_report/controllers/__init__.py
odoo/addons/stock_picking_product_barcode_report/controllers/main.py
odoo/addons/stock_picking_product_barcode_report/data/paperformat_label.xml
odoo/addons/stock_picking_product_barcode_report/i18n/es.po
odoo/addons/stock_picking_product_barcode_report/i18n/it.po
odoo/addons/stock_picking_product_barcode_report/i18n/stock_picking_product_barcode_report.pot
odoo/addons/stock_picking_product_barcode_report/models/__init__.py
odoo/addons/stock_picking_product_barcode_report/models/ir_actions_report.py
odoo/addons/stock_picking_product_barcode_report/models/product_packaging.py
odoo/addons/stock_picking_product_barcode_report/models/res_company.py
odoo/addons/stock_picking_product_barcode_report/models/res_config_settings.py
odoo/addons/stock_picking_product_barcode_report/readme/CONFIGURE.md
odoo/addons/stock_picking_product_barcode_report/readme/CONTRIBUTORS.md
odoo/addons/stock_picking_product_barcode_report/readme/DESCRIPTION.md
odoo/addons/stock_picking_product_barcode_report/readme/USAGE.md
odoo/addons/stock_picking_product_barcode_report/report/report_base_label.xml
odoo/addons/stock_picking_product_barcode_report/report/report_label_barcode.xml
odoo/addons/stock_picking_product_barcode_report/report/report_label_barcode_quant_package_template.xml
odoo/addons/stock_picking_product_barcode_report/report/report_label_barcode_template.xml
odoo/addons/stock_picking_product_barcode_report/report/report_label_custom.xml
odoo/addons/stock_picking_product_barcode_report/security/ir.model.access.csv
odoo/addons/stock_picking_product_barcode_report/static/description/icon.png
odoo/addons/stock_picking_product_barcode_report/static/description/index.html
odoo_addon_stock_picking_product_barcode_report-18.0.1.0.0.2.dist-info/METADATA
odoo_addon_stock_picking_product_barcode_report-18.0.1.0.0.2.dist-info/WHEEL
odoo_addon_stock_picking_product_barcode_report-18.0.1.0.0.2.dist-info/top_level.txt
odoo_addon_stock_picking_product_barcode_report-18.0.1.0.0.2.dist-info/RECORD
