Metadata-Version: 2.1
Name: odoo-addon-stock_picking_product_barcode_report
Version: 18.0.1.0.0.2
Requires-Python: >=3.10
Requires-Dist: odoo==18.0.*
Requires-Dist: python-barcode
Summary: It provides a wizard to select how many barcodes print.
Home-page: https://github.com/OCA/stock-logistics-barcode
License: AGPL-3
Author: Tecnativa, Odoo Community Association (OCA)
Author-email: support@odoo-community.org
Classifier: Programming Language :: Python
Classifier: Framework :: Odoo
Classifier: Framework :: Odoo :: 18.0
Classifier: License :: OSI Approved :: GNU Affero General Public License v3
